{
  "MapTextTranslation": {
    "MapTextTranslation": {
      "Translation": "Translated Text",
      "M-Bool": false,
      "Value": 0
    }
  },
  "阿罗娜钢盔团和PMC集团合作占领了阿拜多斯学校": {
    "Translation": "阿罗娜钢盔团和PMC集团合作占领了阿拜多斯学校",
    "M-Bool": false,
    "Value": 0
  },
  "阿罗娜比纳不知为何也来到了阿拜多斯学校": {
    "Translation": "阿罗娜比纳不知为何也来到了阿拜多斯学校",
    "M-Bool": false,
    "Value": 0
  },
  "阿罗娜好在星野她们已经安全撤出学校了": {
    "Translation": "阿罗娜好在星野她们已经安全撤出学校了",
    "M-Bool": false,
    "Value": 0
  },
  "阿罗娜sensei，我们得想办法把学校夺回来": {
    "Translation": "阿罗娜sensei，我们得想办法把学校夺回来",
    "M-Bool": false,
    "Value": 0
  }
}