{
  "MapTextTranslation": {
    "MapTextTranslation": {
      "Translation": "Translated Text",
      "M-Bool": false,
      "Value": 0
    }
  },
  "Boatescape888 Ver: 1.9.2": {
    "Translation": "Boatescape888 Ver: 1.9.2",
    "M-Bool": false,
    "Value": 0
  },
  "Map by Tsumugi": {
    "Translation": "Map by Tsumugi",
    "M-Bool": false,
    "Value": 0
  },
  " Music: Avid  SawanoHiroyuki[nZk] / 瑞葵(mizuki) ": {
    "Translation": " Music: Avid  SawanoHiroyuki[nZk] / 瑞葵(mizuki) ",
    "M-Bool": false,
    "Value": 0
  },
  " Music: ANIMA  ReoNa ": {
    "Translation": " Music: ANIMA  ReoNa ",
    "M-Bool": false,
    "Value": 0
  },
  " Music: 優しさの記憶  Kano ": {
    "Translation": " Music: 優しさの記憶  Kano ",
    "M-Bool": false,
    "Value": 0
  },
  " Music: wavy flow  Aimer ": {
    "Translation": " Music: wavy flow  Aimer ",
    "M-Bool": false,
    "Value": 0
  },
  " Music: 刀ピー Dilemma~  ピーナッツくん ": {
    "Translation": " Music: 刀ピー Dilemma~  ピーナッツくん ",
    "M-Bool": false,
    "Value": 0
  },
  " Music: root_C / =ALL  桃華なゆた ": {
    "Translation": " Music: root_C / =ALL  桃華なゆた ",
    "M-Bool": false,
    "Value": 0
  },
  " Music: 繭色(まゆいろ)  Sajou no hana ": {
    "Translation": " Music: 繭色(まゆいろ)  Sajou no hana ",
    "M-Bool": false,
    "Value": 0
  },
  " Music: 回马枪  兰音Reine ": {
    "Translation": " Music: 回马枪  兰音Reine ",
    "M-Bool": false,
    "Value": 0
  },
  " Music: 永遠の花が降る  左右田左 ": {
    "Translation": " Music: 永遠の花が降る  左右田左 ",
    "M-Bool": false,
    "Value": 0
  },
  " Music: Hidden Heart  HOYOMiX / Hanser ": {
    "Translation": " Music: Hidden Heart  HOYOMiX / Hanser ",
    "M-Bool": false,
    "Value": 0
  },
  " Music: 始まりの星  出口陽 ": {
    "Translation": " Music: 始まりの星  出口陽 ",
    "M-Bool": false,
    "Value": 0
  },
  " Music: Listen Up  3L ": {
    "Translation": " Music: Listen Up  3L ",
    "M-Bool": false,
    "Value": 0
  },
  " Music: FAKEit  SawanoHiroyuki[nZk] / Laco ": {
    "Translation": " Music: FAKEit  SawanoHiroyuki[nZk] / Laco ",
    "M-Bool": false,
    "Value": 0
  },
  "The door will close in 10 seconds": {
    "Translation": "The door will close in 10 seconds",
    "M-Bool": false,
    "Value": 0
  },
  "The jet boat will depart in 18 seconds": {
    "Translation": "The jet boat will depart in 18 seconds",
    "M-Bool": false,
    "Value": 0
  },
  "The boat will depart in 25 seconds": {
    "Translation": "The boat will depart in 25 seconds",
    "M-Bool": false,
    "Value": 0
  },
  "The airboat will depart in 28 seconds": {
    "Translation": "The airboat will depart in 28 seconds",
    "M-Bool": false,
    "Value": 0
  },
  " Music: UntiL 100SR2  ASCA / 瑞葵(mizuki) ": {
    "Translation": " Music: UntiL 100SR2  ASCA / 瑞葵(mizuki) ",
    "M-Bool": false,
    "Value": 0
  },
  "The door will close in 20 seconds": {
    "Translation": "The door will close in 20 seconds",
    "M-Bool": false,
    "Value": 0
  },
  "Airboats will depart in 30 seconds": {
    "Translation": "Airboats will depart in 30 seconds",
    "M-Bool": false,
    "Value": 0
  },
  "If you dont want to participate, go to the boat on the right": {
    "Translation": "If you dont want to participate, go to the boat on the right",
    "M-Bool": false,
    "Value": 0
  },
  " Music: 朝が来る  Aimer ": {
    "Translation": " Music: 朝が来る  Aimer ",
    "M-Bool": false,
    "Value": 0
  },
  "Baka!!!": {
    "Translation": "Baka!!!",
    "M-Bool": false,
    "Value": 0
  },
  " Music: 境界線  Amazarashi ": {
    "Translation": " Music: 境界線  Amazarashi ",
    "M-Bool": false,
    "Value": 0
  },
  " Music: Resolution  市松椿 ": {
    "Translation": " Music: Resolution  市松椿 ",
    "M-Bool": false,
    "Value": 0
  },
  "Extreme Mode : On": {
    "Translation": "Extreme Mode : On",
    "M-Bool": false,
    "Value": 0
  },
  " Music: ラグトレイン  稲葉曇 / 歌愛ユキ ": {
    "Translation": " Music: ラグトレイン  稲葉曇 / 歌愛ユキ ",
    "M-Bool": false,
    "Value": 0
  },
  " Music: それを世界と言うんだね  かふ ": {
    "Translation": " Music: それを世界と言うんだね  かふ ",
    "M-Bool": false,
    "Value": 0
  },
  " Music: Spring Comes Along  Mican ": {
    "Translation": " Music: Spring Comes Along  Mican ",
    "M-Bool": false,
    "Value": 0
  },
  "Super Run": {
    "Translation": "Super Run",
    "M-Bool": false,
    "Value": 0
  },
  "EndRound": {
    "Translation": "EndRound",
    "M-Bool": false,
    "Value": 0
  },
  "SuperRun": {
    "Translation": "SuperRun",
    "M-Bool": false,
    "Value": 0
  },
  " 5 ": {
    "Translation": " 5 ",
    "M-Bool": false,
    "Value": 0
  },
  " 4 ": {
    "Translation": " 4 ",
    "M-Bool": false,
    "Value": 0
  },
  " 3 ": {
    "Translation": " 3 ",
    "M-Bool": false,
    "Value": 0
  },
  " 2 ": {
    "Translation": " 2 ",
    "M-Bool": false,
    "Value": 0
  },
  " 1 ": {
    "Translation": " 1 ",
    "M-Bool": false,
    "Value": 0
  },
  "Boatescape888 Ver: 1.9.4": {
    "Translation": "Boatescape888 Ver: 1.9.4",
    "M-Bool": false,
    "Value": 0
  },
  " Music: 一笑江湖  兰音Reine ": {
    "Translation": " Music: 一笑江湖  兰音Reine ",
    "M-Bool": false,
    "Value": 0
  },
  " Music: Linking Starlights  Murder Ground ": {
    "Translation": " Music: Linking Starlights  Murder Ground ",
    "M-Bool": false,
    "Value": 0
  },
  " Music: FAKEit - SawanoHiroyuki[nZk] / Laco ": {
    "Translation": " Music: FAKEit - SawanoHiroyuki[nZk] / Laco ",
    "M-Bool": false,
    "Value": 0
  },
  " Music: Avid - SawanoHiroyuki[nZk] / 瑞葵(mizuki) ": {
    "Translation": " Music: Avid - SawanoHiroyuki[nZk] / 瑞葵(mizuki) ",
    "M-Bool": false,
    "Value": 0
  },
  " Music: root_C / =ALL - 桃華なゆた ": {
    "Translation": " Music: root_C / =ALL - 桃華なゆた ",
    "M-Bool": false,
    "Value": 0
  },
  " Music: 刀ピー Dilemma~ - ピーナッツくん ": {
    "Translation": " Music: 刀ピー Dilemma~ - ピーナッツくん ",
    "M-Bool": false,
    "Value": 0
  },
  " Music: 優しさの記憶 - Kano ": {
    "Translation": " Music: 優しさの記憶 - Kano ",
    "M-Bool": false,
    "Value": 0
  },
  " Music: 回马枪 - 兰音Reine ": {
    "Translation": " Music: 回马枪 - 兰音Reine ",
    "M-Bool": false,
    "Value": 0
  },
  " Music: 永遠の花が降る - 左右田左 ": {
    "Translation": " Music: 永遠の花が降る - 左右田左 ",
    "M-Bool": false,
    "Value": 0
  },
  " Music: Listen Up - 3L ": {
    "Translation": " Music: Listen Up - 3L ",
    "M-Bool": false,
    "Value": 0
  },
  " Music: 始まりの星 - 出口陽 ": {
    "Translation": " Music: 始まりの星 - 出口陽 ",
    "M-Bool": false,
    "Value": 0
  },
  " Music: 繭色(まゆいろ) - Sajou no hana ": {
    "Translation": " Music: 繭色(まゆいろ) - Sajou no hana ",
    "M-Bool": false,
    "Value": 0
  },
  " Music: ANIMA - ReoNa ": {
    "Translation": " Music: ANIMA - ReoNa ",
    "M-Bool": false,
    "Value": 0
  }
}