{
  "MapTextTranslation": {
    "MapTextTranslation": {
      "Translation": "Translated Text",
      "M-Bool": false,
      "Value": 0
    }
  },
  "地图作者：ze探险家": {
    "Translation": "Mapper：ze探险家, EN translation: AllenW @ Ozlin server",
    "M-Bool": false,
    "Value": 0
  },
  "祝你游玩愉快": {
    "Translation": "Good luck and have fun",
    "M-Bool": false,
    "Value": 0
  },
  "30 seconds": {
    "Translation": "30 seconds",
    "M-Bool": false,
    "Value": 0
  },
  "tp in 20 seconds": {
    "Translation": "tp in 20 seconds",
    "M-Bool": false,
    "Value": 0
  },
  "30 seconds left": {
    "Translation": "30 seconds left",
    "M-Bool": false,
    "Value": 0
  },
  "僵尸被阻挡 10 seconds": {
    "Translation": "Zombie blocked 10 seconds",
    "M-Bool": false,
    "Value": 0
  },
  "一楼梯子即将打开 5 seconds left": {
    "Translation": "First floor ladder will open in 5 seconds left",
    "M-Bool": false,
    "Value": 0
  },
  "二楼梯子即将打开 5 seconds left": {
    "Translation": "Second floor ladder will open in 5 seconds left",
    "M-Bool": false,
    "Value": 0
  },
  "三楼梯子即将打开 5 seconds left": {
    "Translation": "Third floor ladder will open in 5 seconds left",
    "M-Bool": false,
    "Value": 0
  },
  "20 seconds": {
    "Translation": "20 seconds",
    "M-Bool": false,
    "Value": 0
  },
  "tp in 10 seconds": {
    "Translation": "tp in 10 seconds",
    "M-Bool": false,
    "Value": 0
  },
  "20 seconds left": {
    "Translation": "20 seconds left",
    "M-Bool": false,
    "Value": 0
  },
  "zombie tp in 10 seconds left": {
    "Translation": "Zombie tp in 10 seconds left",
    "M-Bool": false,
    "Value": 0
  },
  "快跑，否则要进入二次元了 !": {
    "Translation": "Run fast, or you will squashed into 2D!",
    "M-Bool": false,
    "Value": 0
  },
  "tp in 15 seconds left": {
    "Translation": "tp in 15 seconds left",
    "M-Bool": false,
    "Value": 0
  },
  "tp in 25 seconds": {
    "Translation": "tp in 25 seconds",
    "M-Bool": false,
    "Value": 0
  },
  "zombie tp in 10 seconds": {
    "Translation": "Zombie tp in 10 seconds",
    "M-Bool": false,
    "Value": 0
  },
  "tp in 15 seconds": {
    "Translation": "tp in 15 seconds",
    "M-Bool": false,
    "Value": 0
  },
  "僵尸被困住了 10 seconds": {
    "Translation": "Zombie is trapped 10 seconds",
    "M-Bool": false,
    "Value": 0
  },
  "僵尸被阻挡 20 seconds": {
    "Translation": "Zombie blocked 20 seconds",
    "M-Bool": false,
    "Value": 0
  },
  "僵尸被阻挡 20 seconds left": {
    "Translation": "Zombie blocked 20 seconds left",
    "M-Bool": false,
    "Value": 0
  },
  "无限弹药已启动": {
    "Translation": "Unlimited ammo activated",
    "M-Bool": false,
    "Value": 0
  },
  "无限弹药结束": {
    "Translation": "Unlimited ammo ended",
    "M-Bool": false,
    "Value": 0
  }
}
