{
  "MapTextTranslation": {
    "MapTextTranslation": {
      "Translation": "Translated Text",
      "M-Bool": false,
      "Value": 0
    }
  },
  "地图原形:Crystar": {
    "Translation": "Map Prototype: Crystar, EN Translation: Allenw @ Ozlin server",
    "M-Bool": false,
    "Value": 0
  },
  "僵尸5s后传送": {
    "Translation": "Zombies will teleport in 5 seconds.",
    "M-Bool": false,
    "Value": 0
  },
  "等待20s": {
    "Translation": "Wait for 20 seconds.",
    "M-Bool": false,
    "Value": 0
  },
  "僵尸10s后传送": {
    "Translation": "Zombies will teleport in 10 seconds.",
    "M-Bool": false,
    "Value": 0
  },
  "防守15s": {
    "Translation": "Defend for 15 seconds.",
    "M-Bool": false,
    "Value": 0
  },
  "防守25s": {
    "Translation": "Defend for 25 seconds.",
    "M-Bool": false,
    "Value": 0
  },
  "推力已被拾起": {
    "Translation": "Thrust has been picked up.",
    "M-Bool": false,
    "Value": 0
  },
  "僵尸3s后传送": {
    "Translation": "Zombies will teleport in 3 seconds.",
    "M-Bool": false,
    "Value": 0
  },
  "防守30s": {
    "Translation": "Defend for 30 seconds.",
    "M-Bool": false,
    "Value": 0
  },
  "剑核心就绪": {
    "Translation": "Sword core is ready.",
    "M-Bool": false,
    "Value": 0
  },
  "僵尸15s后传送": {
    "Translation": "Zombies will teleport in 15 seconds.",
    "M-Bool": false,
    "Value": 0
  },
  "防守5s，注意撤退": {
    "Translation": "Defend for 5 seconds, prepare to retreat.",
    "M-Bool": false,
    "Value": 0
  },
  "Laser!!!": {
    "Translation": "Laser!!!",
    "M-Bool": false,
    "Value": 0
  },
  "恢复已被拾起": {
    "Translation": "Recovery has been picked up.",
    "M-Bool": false,
    "Value": 0
  },
  "恢复1/3": {
    "Translation": "Recovery 1/3.",
    "M-Bool": false,
    "Value": 0
  },
  "恢复已就绪": {
    "Translation": "Recovery is ready.",
    "M-Bool": false,
    "Value": 0
  },
  "撤退！！！": {
    "Translation": "Retreat!!!",
    "M-Bool": false,
    "Value": 0
  },
  "击碎它": {
    "Translation": "Smash it.",
    "M-Bool": false,
    "Value": 0
  },
  "防守10s": {
    "Translation": "Defend for 10 seconds.",
    "M-Bool": false,
    "Value": 0
  },
  "等待30s": {
    "Translation": "Wait for 30 seconds.",
    "M-Bool": false,
    "Value": 0
  }
}